phenotyping_segmentation/__init__.py
phenotyping_segmentation/pipeline.py
phenotyping_segmentation/time.py
phenotyping_segmentation/post_processing/__init__.py
phenotyping_segmentation/post_processing/buffer.py
phenotyping_segmentation/post_processing/remove_boundary.py
phenotyping_segmentation/post_processing/remove_right.py
phenotyping_segmentation/post_processing/remove_unconnected.py
phenotyping_segmentation/post_processing/stitch_crop.py
phenotyping_segmentation/pre_processing/__init__.py
phenotyping_segmentation/pre_processing/add_left_to_right.py
phenotyping_segmentation/pre_processing/crop_image_roi.py
phenotyping_segmentation/pre_processing/crop_pad.py
phenotyping_segmentation/pre_processing/jpg_to_png.py
phenotyping_segmentation/segmentation/__init__.py
phenotyping_segmentation/segmentation/augmentation.py
phenotyping_segmentation/segmentation/color.py
phenotyping_segmentation/segmentation/dataset.py
phenotyping_segmentation/segmentation/metadata.py
phenotyping_segmentation/segmentation/model_parameters.py
phenotyping_segmentation/segmentation/one_hot.py
phenotyping_segmentation/segmentation/preprocessing.py
phenotyping_segmentation/traits/__init__.py
phenotyping_segmentation/traits/area.py
phenotyping_segmentation/traits/convex_hull.py
phenotyping_segmentation/traits/d95.py
phenotyping_segmentation/traits/ellipse.py
phenotyping_segmentation/traits/get_traits.py
phenotyping_segmentation/traits/height_width.py
phenotyping_segmentation/traits/layer_traits.py
phenotyping_segmentation/traits/scanline.py
phenotyping_segmentation/traits/sdxy.py
phenotyping_segmentation/traits/shoot.py
phenotyping_segmentation/traits/skeleton.py
phenotyping_segmentation/traits/summary.py
phenotyping_segmentation/utils/__init_.py
phenotyping_segmentation/utils/imglist.py
phenotyping_segmentation/utils/subfolder.py
phenotyping_segmentation-0.1.8.dist-info/licenses/LICENSE
tests/__init__.py
tests/test_pipeline.py
tests/fixtures/__init__.py
tests/fixtures/data.py
tests/post_processing/__init__.py
tests/post_processing/test_buffer.py
phenotyping_segmentation-0.1.8.dist-info/METADATA
phenotyping_segmentation-0.1.8.dist-info/WHEEL
phenotyping_segmentation-0.1.8.dist-info/top_level.txt
phenotyping_segmentation-0.1.8.dist-info/RECORD
