Metadata-Version: 2.4
Name: phenotyping-segmentation
Version: 0.1.8
Summary: A segmentation pipeline for phenotyping
Author-email: Lin Wang <wanglin9926@gmail.com>
License: MIT License
Requires-Python: >=3.8
License-File: LICENSE
Requires-Dist: numpy
Requires-Dist: pandas
Requires-Dist: scipy
Requires-Dist: opencv-python-headless
Requires-Dist: torch==1.11.0
Requires-Dist: scikit-learn
Requires-Dist: segmentation-models-pytorch
Requires-Dist: albumentations
Requires-Dist: matplotlib
Requires-Dist: seaborn
Requires-Dist: ipywidgets
Requires-Dist: rich
Requires-Dist: jupyter
Requires-Dist: scikit-image
Dynamic: license-file
